[{"id":"PSA.91.1","book":"PSA","bookName":"Psalms","bookNameZh":"詩篇","chapter":91,"verse":1,"ref":"Psalms 91:1","en":"He who dwells in the shelter of the Most High will abide in the shadow of the Almighty.","zh":"住在至高者的隱密處的， 必在全能者的蔭庇下安居。"},{"id":"PSA.91.2","book":"PSA","bookName":"Psalms","bookNameZh":"詩篇","chapter":91,"verse":2,"ref":"Psalms 91:2","en":"I will say to the LORD, \"My refuge and my fortress, my God, in whom I trust.\"","zh":"我要對耶和華說： “你是我的避難所，我的保障， 你是我的 神，我所倚靠的。”"},{"id":"PSA.91.3","book":"PSA","bookName":"Psalms","bookNameZh":"詩篇","chapter":91,"verse":3,"ref":"Psalms 91:3","en":"For he will deliver you from the snare of the fowler and from the deadly pestilence.","zh":"他必救你脫離捕鳥的人的網羅， 脫離致命的瘟疫。"},{"id":"PSA.91.4","book":"PSA","bookName":"Psalms","bookNameZh":"詩篇","chapter":91,"verse":4,"ref":"Psalms 91:4","en":"He will cover you with his pinions, and under his wings you will find refuge; his faithfulness is a shield and buckler.","zh":"他必用自己的羽毛遮蓋你， 你要投靠在他的翅膀底下； 他的信實像盾牌，像堅壘。"},{"id":"PSA.91.5","book":"PSA","bookName":"Psalms","bookNameZh":"詩篇","chapter":91,"verse":5,"ref":"Psalms 91:5","en":"You will not fear the terror of the night, nor the arrow that flies by day,","zh":"你不必害怕黑夜的驚恐， 或是白日的飛箭；"},{"id":"PSA.91.6","book":"PSA","bookName":"Psalms","bookNameZh":"詩篇","chapter":91,"verse":6,"ref":"Psalms 91:6","en":"nor the pestilence that stalks in darkness, nor the destruction that wastes at noonday.","zh":"也不必害怕黑暗中流行的瘟疫， 或是在正午把人毀滅的毒病。"},{"id":"PSA.91.7","book":"PSA","bookName":"Psalms","bookNameZh":"詩篇","chapter":91,"verse":7,"ref":"Psalms 91:7","en":"A thousand may fall at your side, ten thousand at your right hand, but it will not come near you.","zh":"雖有千人仆倒在你的左邊， 萬人仆倒在你的右邊， 但災害必不臨近你。"},{"id":"PSA.91.8","book":"PSA","bookName":"Psalms","bookNameZh":"詩篇","chapter":91,"verse":8,"ref":"Psalms 91:8","en":"You will only look with your eyes and see the recompense of the wicked.","zh":"不過你要親眼觀看， 看見惡人遭報。"},{"id":"PSA.91.9","book":"PSA","bookName":"Psalms","bookNameZh":"詩篇","chapter":91,"verse":9,"ref":"Psalms 91:9","en":"Because you have made the LORD your dwelling place- the Most High, who is my refuge-","zh":"你既然把耶和華當作自己的避難所， 把至高者當作自己的居所，"},{"id":"PSA.91.10","book":"PSA","bookName":"Psalms","bookNameZh":"詩篇","chapter":91,"verse":10,"ref":"Psalms 91:10","en":"no evil shall be allowed to befall you, no plague come near your tent.","zh":"禍患必不臨到你， 災害必不臨近你的帳棚。"},{"id":"PSA.91.11","book":"PSA","bookName":"Psalms","bookNameZh":"詩篇","chapter":91,"verse":11,"ref":"Psalms 91:11","en":"For he will command his angels concerning you to guard you in all your ways.","zh":"因為他為了你，會吩咐自己的使者， 在你所行的一切路上保護你。"},{"id":"PSA.91.12","book":"PSA","bookName":"Psalms","bookNameZh":"詩篇","chapter":91,"verse":12,"ref":"Psalms 91:12","en":"On their hands they will bear you up, lest you strike your foot against a stone.","zh":"他們必用手托住你， 免得你的腳碰到石頭。"},{"id":"PSA.91.13","book":"PSA","bookName":"Psalms","bookNameZh":"詩篇","chapter":91,"verse":13,"ref":"Psalms 91:13","en":"You will tread on the lion and the adder; the young lion and the serpent you will trample underfoot.","zh":"你必踐踏獅子和虺蛇。 你必踏碎少壯獅子和大蛇。"},{"id":"PSA.91.14","book":"PSA","bookName":"Psalms","bookNameZh":"詩篇","chapter":91,"verse":14,"ref":"Psalms 91:14","en":"\"Because he holds fast to me in love, I will deliver him; I will protect him, because he knows my name.","zh":"耶和華說：“因為他戀慕我，我必搭救他； 因為他認識我的名，我必保護他。"},{"id":"PSA.91.15","book":"PSA","bookName":"Psalms","bookNameZh":"詩篇","chapter":91,"verse":15,"ref":"Psalms 91:15","en":"When he calls to me, I will answer him; I will be with him in trouble; I will rescue him and honor him.","zh":"他求告我，我必應允他； 他在患難中，我必與他同在； 我必拯救他，使他得尊榮。"},{"id":"PSA.91.16","book":"PSA","bookName":"Psalms","bookNameZh":"詩篇","chapter":91,"verse":16,"ref":"Psalms 91:16","en":"With long life I will satisfy him and show him my salvation.\"","zh":"我必使他得享長壽， 又向他顯明我的救恩。”"}]